<annotation>
	<folder>1</folder>
	<filename>221.jpg</filename>
	<path>C:\Users\LIZHIMING1\Desktop\orange\1\221.jpg</path>
	<source>
		<database>Unknown</database>
	</source>
	<size>
		<width>183</width>
		<height>275</height>
		<depth>3</depth>
	</size>
	<segmented>0</segmented>
	<object>
		<name>orange</name>
		<pose>Unspecified</pose>
		<truncated>0</truncated>
		<difficult>0</difficult>
		<bndbox>
			<xmin>7</xmin>
			<ymin>131</ymin>
			<xmax>79</xmax>
			<ymax>190</ymax>
		</bndbox>
	</object>
	<object>
		<name>orange</name>
		<pose>Unspecified</pose>
		<truncated>0</truncated>
		<difficult>0</difficult>
		<bndbox>
			<xmin>14</xmin>
			<ymin>186</ymin>
			<xmax>80</xmax>
			<ymax>246</ymax>
		</bndbox>
	</object>
	<object>
		<name>orange</name>
		<pose>Unspecified</pose>
		<truncated>0</truncated>
		<difficult>0</difficult>
		<bndbox>
			<xmin>86</xmin>
			<ymin>127</ymin>
			<xmax>153</xmax>
			<ymax>196</ymax>
		</bndbox>
	</object>
	<object>
		<name>orange</name>
		<pose>Unspecified</pose>
		<truncated>0</truncated>
		<difficult>0</difficult>
		<bndbox>
			<xmin>39</xmin>
			<ymin>89</ymin>
			<xmax>107</xmax>
			<ymax>147</ymax>
		</bndbox>
	</object>
	<object>
		<name>orange</name>
		<pose>Unspecified</pose>
		<truncated>0</truncated>
		<difficult>0</difficult>
		<bndbox>
			<xmin>34</xmin>
			<ymin>44</ymin>
			<xmax>83</xmax>
			<ymax>96</ymax>
		</bndbox>
	</object>
	<object>
		<name>orange</name>
		<pose>Unspecified</pose>
		<truncated>0</truncated>
		<difficult>0</difficult>
		<bndbox>
			<xmin>116</xmin>
			<ymin>181</ymin>
			<xmax>182</xmax>
			<ymax>239</ymax>
		</bndbox>
	</object>
</annotation>
